certbot_plugin_gandi/__init__.py
certbot_plugin_gandi/gandi_api.py
certbot_plugin_gandi/main.py
certbot_plugin_gandi-1.5.2.dist-info/LICENSE
certbot_plugin_gandi-1.5.2.dist-info/METADATA
certbot_plugin_gandi-1.5.2.dist-info/WHEEL
certbot_plugin_gandi-1.5.2.dist-info/entry_points.txt
certbot_plugin_gandi-1.5.2.dist-info/top_level.txt
certbot_plugin_gandi-1.5.2.dist-info/RECORD
